paint/__init__.py
paint/data/__init__.py
paint/data/dataset.py
paint/data/dataset_splits.py
paint/data/stac_client.py
paint/preprocessing/__init__.py
paint/preprocessing/binary_extractor.py
paint/preprocessing/calibration_stac.py
paint/preprocessing/catalog_stac.py
paint/preprocessing/deflectometry_stac.py
paint/preprocessing/dwd_mappings.py
paint/preprocessing/dwd_stac_item.py
paint/preprocessing/dwd_weather.py
paint/preprocessing/focal_spot_extractor.py
paint/preprocessing/heliostat_catalog_stac.py
paint/preprocessing/juelich_weather_converter.py
paint/preprocessing/juelich_weather_mappings.py
paint/preprocessing/juelich_weather_stac_item.py
paint/preprocessing/properties_stac.py
paint/preprocessing/target_cropper.py
paint/preprocessing/tower_measurements.py
paint/preprocessing/tower_stac.py
paint/preprocessing/weather_collection_stac.py
paint/util/__init__.py
paint/util/gauss_kruger_converter.py
paint/util/paint_mappings.py
paint/util/preprocessing.py
paint/util/renovation_mappings.py
paint/util/utils.py
paint_csp-2.0.1.dist-info/METADATA
paint_csp-2.0.1.dist-info/WHEEL
paint_csp-2.0.1.dist-info/licenses/LICENSE.md
paint_csp-2.0.1.dist-info/RECORD
