Metadata-Version: 2.4
Name: paint-csp
Version: 2.0.1
Summary: A FAIR database for concentrating solar power plant data
Project-URL: Homepage, https://github.com/ARTIST-Association/PAINT
Project-URL: Issues, https://github.com/ARTIST-Association/PAINT/issues
Author-email: ARTIST Consortium <artist@lists.kit.edu>
License-File: LICENSE.md
Classifier: Development Status :: 5 - Production/Stable
Classifier: License :: OSI Approved :: MIT License
Classifier: Programming Language :: Python :: 3
Requires-Python: >=3.10
Requires-Dist: colorlog
Requires-Dist: deepdiff
Requires-Dist: flask
Requires-Dist: h5py
Requires-Dist: matplotlib
Requires-Dist: numpy
Requires-Dist: opencv-python
Requires-Dist: openpyxl
Requires-Dist: pandas
Requires-Dist: pyproj
Requires-Dist: pystac
Requires-Dist: pytz
Requires-Dist: seaborn
Requires-Dist: torch
Requires-Dist: torchvision
Requires-Dist: waitress
Requires-Dist: wetterdienst==0.95.1
Provides-Extra: dev
Requires-Dist: coverage<7.6.5; extra == 'dev'
Requires-Dist: pre-commit; extra == 'dev'
Requires-Dist: pytest; extra == 'dev'
Requires-Dist: pytest-cov; extra == 'dev'
Requires-Dist: ruff; extra == 'dev'
Requires-Dist: sphinx-autoapi; extra == 'dev'
Requires-Dist: sphinx-rtd-theme; extra == 'dev'
Requires-Dist: sphinxcontrib-napoleon; extra == 'dev'
Requires-Dist: sphinxemoji; extra == 'dev'
Provides-Extra: tutorial
Requires-Dist: jupyter; extra == 'tutorial'
